nuclearowl/__init__.py
nuclearowl/debug.py
nuclearowl/file.py
nuclearowl/mips.py
nuclearowl/sample_masks.py
nuclearowl/wrappers.py
nuclearowl/nifti/__init__.py
nuclearowl/nifti/fileIO.py
nuclearowl/nifti/operations.py
nuclearowl/nifti/segmentator.py
nuclearowl/nifti/suv_lib.py
nuclearowl/nifti/utils.py
nuclearowl/operations/__init__.py
nuclearowl/operations/analysis.py
nuclearowl/operations/file.py
nuclearowl/operations/kernels.py
nuclearowl/operations/mask.py
nuclearowl/operations/utils.py
nuclearowl-1.1.0.dist-info/LICENSE
nuclearowl-1.1.0.dist-info/LICENSE-APACHE
nuclearowl-1.1.0.dist-info/METADATA
nuclearowl-1.1.0.dist-info/NOTICE
nuclearowl-1.1.0.dist-info/WHEEL
nuclearowl-1.1.0.dist-info/top_level.txt
nuclearowl-1.1.0.dist-info/RECORD
