Metadata-Version: 2.1
Name: nuclearowl
Version: 1.1.0
Summary: A lib handling nuclear imaging data and Ai applications on top of it
Home-page: https://github.com/eser-chr/nuclearowl
Author: eser-chr
Author-email: chriseseroglou@gmail.com
License: MIT
Keywords: nuclear imaging,medical imaging,python,AI(wow),segmentation
Classifier: Development Status :: 3 - Alpha
Classifier: Intended Audience :: Developers
Classifier: Topic :: Software Development :: Libraries
Classifier: License :: OSI Approved :: MIT License
Classifier: Programming Language :: Python :: 3
Classifier: Programming Language :: Python :: 3.10
Requires-Python: >=3.7
License-File: LICENSE
License-File: LICENSE-APACHE
License-File: NOTICE
Requires-Dist: dicom2nifti >=2.4.11
Requires-Dist: matplotlib >=3.9.2
Requires-Dist: nibabel >=5.2.1
Requires-Dist: numpy >=1.26.4
Requires-Dist: pandas >=2.2.2
Requires-Dist: pydicom >=2.4.4
Requires-Dist: Pygments >=2.18.0
Requires-Dist: scipy >=1.14.1
Requires-Dist: torch >=2.4.0
Requires-Dist: TotalSegmentator >=2.4.0
